genderClassifier-1.8.dist-info/METADATA
genderClassifier-1.8.dist-info/RECORD
genderClassifier-1.8.dist-info/WHEEL
genderClassifier-1.8.dist-info/top_level.txt
gender_classifier/__init__.py
gender_classifier/classifier.py
gender_classifier/download.py
